transloadit/__init__.py
transloadit/assembly.py
transloadit/client.py
transloadit/optionbuilder.py
transloadit/request.py
transloadit/response.py
transloadit/template.py
pytransloadit-1.0.2.dist-info/LICENSE
pytransloadit-1.0.2.dist-info/METADATA
pytransloadit-1.0.2.dist-info/WHEEL
pytransloadit-1.0.2.dist-info/RECORD
