Metadata-Version: 2.1
Name: pytransloadit
Version: 1.0.2
Summary: A Python Integration for Transloadit's file uploading and encoding service.
Home-page: https://github.com/transloadit/python-sdk
License: MIT
Author: Ifedapo Olarewaju
Maintainer: Florian Kuenzig
Requires-Python: >=3.9
Classifier: Development Status :: 3 - Alpha
Classifier: Environment :: Web Environment
Classifier: Intended Audience :: Developers
Classifier: License :: OSI Approved :: MIT License
Classifier: Natural Language :: English
Classifier: Operating System :: OS Independent
Classifier: Programming Language :: Python
Classifier: Programming Language :: Python :: 3
Classifier: Programming Language :: Python :: 3.9
Classifier: Programming Language :: Python :: 3.10
Classifier: Programming Language :: Python :: 3.11
Classifier: Programming Language :: Python :: 3.12
Classifier: Programming Language :: Python :: 3.13
Classifier: Topic :: Communications :: File Sharing
Classifier: Topic :: Internet :: File Transfer Protocol (FTP)
Classifier: Topic :: Multimedia :: Sound/Audio :: Conversion
Classifier: Topic :: Multimedia :: Video :: Conversion
Classifier: Topic :: Software Development :: Libraries :: Python Modules
Requires-Dist: requests (>=2.30.0,<3.0.0)
Requires-Dist: tuspy (>=1.0.0,<2.0.0)
Project-URL: Documentation, https://transloadit.readthedocs.io
Project-URL: Repository, https://github.com/transloadit/python-sdk
